vsax/__init__.py
vsax/py.typed
vsax/core/__init__.py
vsax/core/base.py
vsax/core/factory.py
vsax/core/memory.py
vsax/core/model.py
vsax/encoders/__init__.py
vsax/encoders/base.py
vsax/encoders/dict.py
vsax/encoders/fpe.py
vsax/encoders/graph.py
vsax/encoders/scalar.py
vsax/encoders/sequence.py
vsax/encoders/set.py
vsax/io/__init__.py
vsax/io/load.py
vsax/io/save.py
vsax/operators/__init__.py
vsax/operators/base.py
vsax/operators/clifford.py
vsax/operators/kinds.py
vsax/operators/semantic.py
vsax/operators/spatial.py
vsax/ops/__init__.py
vsax/ops/binary.py
vsax/ops/fhrr.py
vsax/ops/map.py
vsax/ops/quaternion.py
vsax/representations/__init__.py
vsax/representations/binary_hv.py
vsax/representations/complex_hv.py
vsax/representations/quaternion_hv.py
vsax/representations/real_hv.py
vsax/resonator/__init__.py
vsax/resonator/cleanup.py
vsax/resonator/resonator.py
vsax/sampling/__init__.py
vsax/sampling/random.py
vsax/similarity/__init__.py
vsax/similarity/cosine.py
vsax/similarity/dot.py
vsax/similarity/hamming.py
vsax/similarity/quaternion.py
vsax/spatial/__init__.py
vsax/spatial/ssp.py
vsax/spatial/utils.py
vsax/utils/__init__.py
vsax/utils/batch.py
vsax/utils/coerce.py
vsax/utils/device.py
vsax/utils/repr.py
vsax/utils/validation.py
vsax/vfa/__init__.py
vsax/vfa/applications.py
vsax/vfa/function_encoder.py
vsax/vfa/kernels.py
vsax-1.4.1.dist-info/licenses/LICENSE
vsax-1.4.1.dist-info/METADATA
vsax-1.4.1.dist-info/WHEEL
vsax-1.4.1.dist-info/top_level.txt
vsax-1.4.1.dist-info/RECORD
