Metadata-Version: 2.4
Name: vsax
Version: 1.4.1
Summary: JAX-native Vector Symbolic Algebra library
Author-email: Vasanth Sarathy <vsarathy@gmail.com>
License-Expression: MIT
Project-URL: Homepage, https://github.com/vasanthsarathy/vsax
Project-URL: Documentation, https://vasanthsarathy.github.io/vsax/
Project-URL: Repository, https://github.com/vasanthsarathy/vsax
Project-URL: Issues, https://github.com/vasanthsarathy/vsax/issues
Keywords: vector-symbolic-architectures,hyperdimensional-computing,jax,vsa,hdc,fhrr,map,cognitive-computing
Classifier: Development Status :: 5 - Production/Stable
Classifier: Intended Audience :: Science/Research
Classifier: Intended Audience :: Developers
Classifier: Programming Language :: Python :: 3
Classifier: Programming Language :: Python :: 3.9
Classifier: Programming Language :: Python :: 3.10
Classifier: Programming Language :: Python :: 3.11
Classifier: Programming Language :: Python :: 3.12
Classifier: Topic :: Scientific/Engineering :: Artificial Intelligence
Classifier: Topic :: Scientific/Engineering :: Mathematics
Requires-Python: >=3.9
License-File: LICENSE
Requires-Dist: jax>=0.4.20
Requires-Dist: jaxlib>=0.4.20
Requires-Dist: marimo>=0.17.6
Requires-Dist: matplotlib>=3.9.4
Requires-Dist: numpy>=1.24.0
Provides-Extra: dev
Requires-Dist: pytest>=7.4.0; extra == "dev"
Requires-Dist: pytest-cov>=4.1.0; extra == "dev"
Requires-Dist: ruff>=0.1.0; extra == "dev"
Requires-Dist: mypy>=1.7.0; extra == "dev"
Requires-Dist: types-setuptools>=69.0.0; extra == "dev"
Provides-Extra: docs
Requires-Dist: mkdocs>=1.5.0; extra == "docs"
Requires-Dist: mkdocs-material>=9.4.0; extra == "docs"
Requires-Dist: mkdocstrings[python]>=0.24.0; extra == "docs"
Dynamic: license-file
